netcoloc/__init__.py
netcoloc/cli.py
netcoloc/netcoloc_utils.py
netcoloc/netprop.py
netcoloc/netprop_zscore.py
netcoloc/network_colocalization.py
netcoloc/validation.py
netcoloc-0.1.7.dist-info/AUTHORS.rst
netcoloc-0.1.7.dist-info/LICENSE
netcoloc-0.1.7.dist-info/METADATA
netcoloc-0.1.7.dist-info/WHEEL
netcoloc-0.1.7.dist-info/entry_points.txt
netcoloc-0.1.7.dist-info/top_level.txt
netcoloc-0.1.7.dist-info/RECORD
