Metadata-Version: 2.1
Name: netcoloc
Version: 0.1.7
Summary: UNKNOWN
Home-page: https://github.com/ucsd-ccbb/netcoloc
Author: Brin Rosenthal, Sophie Liu
Author-email: sbrosenthal@health.ucsd.edu, sol015@ucsd.edu
License: MIT license
Keywords: netcoloc
Platform: UNKNOWN
Classifier: Development Status :: 2 - Pre-Alpha
Classifier: Intended Audience :: Developers
Classifier: License :: OSI Approved :: MIT License
Classifier: Natural Language :: English
Classifier: Programming Language :: Python :: 2.7
Classifier: Programming Language :: Python :: 3
Classifier: Programming Language :: Python :: 3.3
Classifier: Programming Language :: Python :: 3.4
Classifier: Programming Language :: Python :: 3.5
Requires-Dist: click (>=6.0)
Requires-Dist: ndex2
Requires-Dist: networkx (>=2.0)
Requires-Dist: mygene (>=3.2.2)
Requires-Dist: scipy (>=1.5.3)
Requires-Dist: numpy
Requires-Dist: pandas
Requires-Dist: tqdm
Requires-Dist: matplotlib
Requires-Dist: seaborn
Requires-Dist: statsmodels
Requires-Dist: gprofiler-official (>=1.0.0)
Requires-Dist: ipycytoscape
Requires-Dist: ipywidgets
